port_calibration/__init__.py
port_calibration/one_port.py
port_calibration/two_port.py
port_calibration/utils.py
port_calibration-0.14.dist-info/METADATA
port_calibration-0.14.dist-info/WHEEL
port_calibration-0.14.dist-info/top_level.txt
port_calibration-0.14.dist-info/RECORD
