Metadata-Version: 2.4
Name: port-calibration
Version: 0.14
Summary: SIS calibration
Home-page: https://github.com/yarvod/port-calibration
Author: yarvod
Author-email: ya.vodzyanovskiy@lebedev.ru
Keywords: port calibration vna
Requires-Dist: numpy
Dynamic: author
Dynamic: author-email
Dynamic: description
Dynamic: description-content-type
Dynamic: home-page
Dynamic: keywords
Dynamic: requires-dist
Dynamic: summary
